stocktopus/__init__.py
stocktopus/__main__.py
stocktopus/_version.py
stocktopus/driver.py
stocktopus/main.py
stocktopus/paramspec_from.py
stocktopus/process.py
stocktopus/types.py
stocktopus/degiro/__init__.py
stocktopus/degiro/main.py
stocktopus/degiro/parse.py
stocktopus/interactive_brokers/__init__.py
stocktopus/interactive_brokers/main.py
stocktopus/interactive_brokers/parse.py
stocktopus/parserlib/__init__.py
stocktopus/parserlib/load.py
stocktopus/parserlib/parse.py
stocktopus-0.1.dist-info/METADATA
stocktopus-0.1.dist-info/WHEEL
stocktopus-0.1.dist-info/entry_points.txt
stocktopus-0.1.dist-info/top_level.txt
stocktopus-0.1.dist-info/RECORD
