Metadata-Version: 2.1
Name: stocktopus
Version: 0.1
Summary: automatically fill-in tax forms
Home-page: https://gitlab.com/martizih/stocktopus.git
Author: Martin Zihlmann
Author-email: martizih@outlook.com
License: MIT
Classifier: Programming Language :: Python :: 3
Classifier: License :: Other/Proprietary License
Classifier: Operating System :: OS Independent
Requires-Python: >=3.10
Requires-Dist: pyaml
Requires-Dist: selenium
Requires-Dist: tipsy
Requires-Dist: typer
Requires-Dist: xmltodict
